stocksim/__init__.py
stocksim/main.py
stocksim-1.3.3.dist-info/licenses/LICENSE
stocksim-1.3.3.dist-info/METADATA
stocksim-1.3.3.dist-info/WHEEL
stocksim-1.3.3.dist-info/entry_points.txt
stocksim-1.3.3.dist-info/top_level.txt
stocksim-1.3.3.dist-info/RECORD
