Metadata-Version: 2.4
Name: stocksim
Version: 1.3.3
Summary: Monte Carlo Stock/Crypto Price Simulation Tool
Home-page: https://github.com/ElementalPublishing/StockSim
Author: Wesley Alexander Houser
Author-email: houser2388@gmail.com
License: MIT
Project-URL: Source, https://github.com/ElementalPublishing/StockSim
Project-URL: Tracker, https://github.com/ElementalPublishing/StockSim/issues
Classifier: Programming Language :: Python :: 3
Classifier: Programming Language :: Python :: 3.7
Classifier: Programming Language :: Python :: 3.8
Classifier: Programming Language :: Python :: 3.9
Classifier: Programming Language :: Python :: 3.10
Classifier: Programming Language :: Python :: 3.11
Classifier: License :: OSI Approved :: MIT License
Classifier: Operating System :: OS Independent
Classifier: Intended Audience :: End Users/Desktop
Classifier: Intended Audience :: Developers
Classifier: Topic :: Software Development :: Libraries :: Application Frameworks
Classifier: Topic :: Utilities
Requires-Python: >=3.7
License-File: LICENSE
Requires-Dist: numpy
Requires-Dist: yfinance
Requires-Dist: psutil
Dynamic: author
Dynamic: author-email
Dynamic: classifier
Dynamic: description
Dynamic: description-content-type
Dynamic: home-page
Dynamic: license
Dynamic: license-file
Dynamic: project-url
Dynamic: requires-dist
Dynamic: requires-python
Dynamic: summary
